[
  {
    "date": "2022-11-23",
    "teams": []
  },
  {
    "date": "2022-11-16",
    "teams": []
  },
  {
    "date": "2022-11-09",
    "teams": []
  },
  {
    "date": "2022-11-02",
    "teams": []
  },
  {
    "date": "2022-10-26",
    "teams": []
  },
  {
    "date": "2022-10-19",
    "teams": [
      {
        "name": "Homers Pin Pals",
        "players": [
          {
            "name": "Anita Tilley",
            "Hcp": 45,
            "Avg": 150,
            "Gms": 0,
            "Pins": 0,
            "Hgs": 0,
            "HSS": 0
          },
          {
            "name": "Paul Bexley",
            "Hcp": 27,
            "Avg": 169,
            "Gms": 3,
            "Pins": 473,
            "Hgs": 170,
            "HSS": 473
          },
          {
            "name": "Jon Ng",
            "Hcp": 38,
            "Avg": 157,
            "Gms": 9,
            "Pins": 1421,
            "Hgs": 190,
            "HSS": 478
          },
          {
            "name": "Gemma Robinson",
            "Hcp": 40,
            "Avg": 155,
            "Gms": 6,
            "Pins": 1014,
            "Hgs": 192,
            "HSS": 537
          },
          {
            "name": "Lewis Place",
            "Hcp": 0,
            "Avg": 0,
            "Gms": 0,
            "Pins": 0,
            "Hgs": 0,
            "HSS": 0
          },
          {
            "name": "Jamie",
            "Hcp": 67,
            "Avg": 125,
            "Gms": 3,
            "Pins": 323,
            "Hgs": 114,
            "HSS": 323
          }
        ]
      },
      {
        "name": "Bomber",
        "players": [
          {
            "name": "Steve Gibson",
            "Hcp": 24,
            "Avg": 173,
            "Gms": 9,
            "Pins": 1558,
            "Hgs": 199,
            "HSS": 530
          },
          {
            "name": "Paul Jackson",
            "Hcp": 30,
            "Avg": 166,
            "Gms": 6,
            "Pins": 961,
            "Hgs": 206,
            "HSS": 525
          },
          {
            "name": "Brian Bagerley",
            "Hcp": 42,
            "Avg": 153,
            "Gms": 9,
            "Pins": 1383,
            "Hgs": 215,
            "HSS": 538
          },
          {
            "name": "Phil Henderson",
            "Hcp": 0,
            "Avg": 0,
            "Gms": 0,
            "Pins": 0,
            "Hgs": 0,
            "HSS": 0
          },
          {
            "name": "Steve Armstrong",
            "Hcp": 52,
            "Avg": 142,
            "Gms": 9,
            "Pins": 1280,
            "Hgs": 164,
            "HSS": 434
          }
        ]
      },
      {
        "name": "Same Again",
        "players": [
          {
            "name": "Tony Corner",
            "Hcp": 33,
            "Avg": 163,
            "Gms": 0,
            "Pins": 0,
            "Hgs": 0,
            "HSS": 0
          },
          {
            "name": "Derek Parton",
            "Hcp": 35,
            "Avg": 161,
            "Gms": 0,
            "Pins": 0,
            "Hgs": 0,
            "HSS": 0
          },
          {
            "name": "Mike Bostock",
            "Hcp": 21,
            "Avg": 176,
            "Gms": 9,
            "Pins": 1590,
            "Hgs": 195,
            "HSS": 545
          },
          {
            "name": "Tina Roche",
            "Hcp": 69,
            "Avg": 123,
            "Gms": 3,
            "Pins": 392,
            "Hgs": 145,
            "HSS": 392
          },
          {
            "name": "Phillip Morton",
            "Hcp": 0,
            "Avg": 0,
            "Gms": 0,
            "Pins": 0,
            "Hgs": 0,
            "HSS": 0
          },
          {
            "name": "Alex Hedley",
            "Hcp": 78,
            "Avg": 113,
            "Gms": 9,
            "Pins": 1022,
            "Hgs": 166,
            "HSS": 367
          }
        ]
      },
      {
        "name": "Skandia Warriors",
        "players": [
          {
            "name": "Michael Henderson",
            "Hcp": 9,
            "Avg": 189,
            "Gms": 9,
            "Pins": 1701,
            "Hgs": 219,
            "HSS": 613
          },
          {
            "name": "Paul Gardner",
            "Hcp": 38,
            "Avg": 157,
            "Gms": 6,
            "Pins": 907,
            "Hgs": 194,
            "HSS": 477
          },
          {
            "name": "Barry Henderson",
            "Hcp": 90,
            "Avg": 99,
            "Gms": 9,
            "Pins": 897,
            "Hgs": 136,
            "HSS": 311
          },
          {
            "name": "Colin Argyle",
            "Hcp": 37,
            "Avg": 158,
            "Gms": 9,
            "Pins": 1427,
            "Hgs": 200,
            "HSS": 519
          }
        ]
      }
    ]
  },
  {
    "date": "2022-10-12",
    "teams": [
      {
        "name": "Homers Pin Pals",
        "players": [
          {
            "name": "Anita Tilley",
            "Hcp": 45,
            "Avg": 150,
            "Gms": 0,
            "Pins": 0,
            "Hgs": 0,
            "HSS": 0
          },
          {
            "name": "Paul Bexley",
            "Hcp": 27,
            "Avg": 169,
            "Gms": 3,
            "Pins": 473,
            "Hgs": 170,
            "HSS": 473
          },
          {
            "name": "Jon Ng",
            "Hcp": 30,
            "Avg": 166,
            "Gms": 6,
            "Pins": 943,
            "Hgs": 190,
            "HSS": 477
          },
          {
            "name": "Gemma Robinson",
            "Hcp": 40,
            "Avg": 155,
            "Gms": 3,
            "Pins": 477,
            "Hgs": 181,
            "HSS": 477
          },
          {
            "name": "Lewis Place",
            "Hcp": 0,
            "Avg": 0,
            "Gms": 0,
            "Pins": 0,
            "Hgs": 0,
            "HSS": 0
          },
          {
            "name": "Jamie",
            "Hcp": 67,
            "Avg": 125,
            "Gms": 3,
            "Pins": 323,
            "Hgs": 114,
            "HSS": 323
          }
        ]
      },
      {
        "name": "Bomber",
        "players": [
          {
            "name": "Steve Gibson",
            "Hcp": 37,
            "Avg": 158,
            "Gms": 6,
            "Pins": 1032,
            "Hgs": 186,
            "HSS": 530
          },
          {
            "name": "Paul Jackson",
            "Hcp": 30,
            "Avg": 166,
            "Gms": 3,
            "Pins": 525,
            "Hgs": 206,
            "HSS": 525
          },
          {
            "name": "Brian Bagerley",
            "Hcp": 45,
            "Avg": 150,
            "Gms": 6,
            "Pins": 949,
            "Hgs": 215,
            "HSS": 538
          },
          {
            "name": "Phil Henderson",
            "Hcp": 0,
            "Avg": 0,
            "Gms": 0,
            "Pins": 0,
            "Hgs": 0,
            "HSS": 0
          },
          {
            "name": "Steve Armstrong",
            "Hcp": 41,
            "Avg": 154,
            "Gms": 6,
            "Pins": 850,
            "Hgs": 164,
            "HSS": 434
          }
        ]
      },
      {
        "name": "Same Again",
        "players": [
          {
            "name": "Tony Corner",
            "Hcp": 33,
            "Avg": 163,
            "Gms": 0,
            "Pins": 0,
            "Hgs": 0,
            "HSS": 0
          },
          {
            "name": "Derek Parton",
            "Hcp": 35,
            "Avg": 161,
            "Gms": 0,
            "Pins": 0,
            "Hgs": 0,
            "HSS": 0
          },
          {
            "name": "Mike Bostock",
            "Hcp": 35,
            "Avg": 161,
            "Gms": 6,
            "Pins": 1048,
            "Hgs": 195,
            "HSS": 545
          },
          {
            "name": "Tina Roche",
            "Hcp": 69,
            "Avg": 123,
            "Gms": 0,
            "Pins": 0,
            "Hgs": 0,
            "HSS": 0
          },
          {
            "name": "Phillip Morton",
            "Hcp": 0,
            "Avg": 0,
            "Gms": 0,
            "Pins": 0,
            "Hgs": 0,
            "HSS": 0
          },
          {
            "name": "Alex Hedley",
            "Hcp": 70,
            "Avg": 122,
            "Gms": 6,
            "Pins": 733,
            "Hgs": 166,
            "HSS": 367
          }
        ]
      },
      {
        "name": "Skandia Warriors",
        "players": [
          {
            "name": "Michael Henderson",
            "Hcp": 20,
            "Avg": 177,
            "Gms": 6,
            "Pins": 1088,
            "Hgs": 187,
            "HSS": 552
          },
          {
            "name": "Paul Gardner",
            "Hcp": 38,
            "Avg": 157,
            "Gms": 6,
            "Pins": 907,
            "Hgs": 194,
            "HSS": 477
          },
          {
            "name": "Barry Henderson",
            "Hcp": 89,
            "Avg": 101,
            "Gms": 6,
            "Pins": 622,
            "Hgs": 136,
            "HSS": 311
          },
          {
            "name": "Colin Argyle",
            "Hcp": 28,
            "Avg": 168,
            "Gms": 6,
            "Pins": 908,
            "Hgs": 186,
            "HSS": 517
          }
        ]
      }
    ]
  },
  {
    "date": "2022-10-05",
    "teams": [
      {
        "name": "Homers Pin Pals",
        "players": [
          {
            "name": "Anita Tilley",
            "Hcp": 45,
            "Avg": 150,
            "Gms": 0,
            "Pins": 0,
            "Hgs": 0,
            "HSS": 0
          },
          {
            "name": "Paul Bexley",
            "Hcp": 27,
            "Avg": 169,
            "Gms": 0,
            "Pins": 0,
            "Hgs": 0,
            "HSS": 0
          },
          {
            "name": "Jon Ng",
            "Hcp": 30,
            "Avg": 166,
            "Gms": 3,
            "Pins": 466,
            "Hgs": 190,
            "HSS": 466
          },
          {
            "name": "Gemma Robinson",
            "Hcp": 40,
            "Avg": 155,
            "Gms": 3,
            "Pins": 477,
            "Hgs": 181,
            "HSS": 477
          },
          {
            "name": "Lewis Place",
            "Hcp": 0,
            "Avg": 0,
            "Gms": 0,
            "Pins": 0,
            "Hgs": 0,
            "HSS": 0
          },
          {
            "name": "Jamie",
            "Hcp": 67,
            "Avg": 125,
            "Gms": 0,
            "Pins": 0,
            "Hgs": 0,
            "HSS": 0
          }
        ]
      },
      {
        "name": "Bomber",
        "players": [
          {
            "name": "Steve Gibson",
            "Hcp": 37,
            "Avg": 158,
            "Gms": 3,
            "Pins": 530,
            "Hgs": 186,
            "HSS": 530
          },
          {
            "name": "Paul Jackson",
            "Hcp": 30,
            "Avg": 166,
            "Gms": 3,
            "Pins": 525,
            "Hgs": 206,
            "HSS": 525
          },
          {
            "name": "Brian Bagerley",
            "Hcp": 45,
            "Avg": 150,
            "Gms": 3,
            "Pins": 411,
            "Hgs": 159,
            "HSS": 411
          },
          {
            "name": "Phil Henderson",
            "Hcp": 0,
            "Avg": 0,
            "Gms": 0,
            "Pins": 0,
            "Hgs": 0,
            "HSS": 0
          },
          {
            "name": "Steve Armstrong",
            "Hcp": 41,
            "Avg": 154,
            "Gms": 3,
            "Pins": 434,
            "Hgs": 164,
            "HSS": 434
          }
        ]
      },
      {
        "name": "Same Again",
        "players": [
          {
            "name": "Tony Corner",
            "Hcp": 33,
            "Avg": 163,
            "Gms": 0,
            "Pins": 0,
            "Hgs": 0,
            "HSS": 0
          },
          {
            "name": "Derek Parton",
            "Hcp": 35,
            "Avg": 161,
            "Gms": 0,
            "Pins": 0,
            "Hgs": 0,
            "HSS": 0
          },
          {
            "name": "Mike Bostock",
            "Hcp": 35,
            "Avg": 161,
            "Gms": 3,
            "Pins": 545,
            "Hgs": 195,
            "HSS": 545
          },
          {
            "name": "Tina Roche",
            "Hcp": 69,
            "Avg": 123,
            "Gms": 0,
            "Pins": 0,
            "Hgs": 0,
            "HSS": 0
          },
          {
            "name": "Phillip Morton",
            "Hcp": 0,
            "Avg": 0,
            "Gms": 0,
            "Pins": 0,
            "Hgs": 0,
            "HSS": 0
          },
          {
            "name": "Alex Hedley",
            "Hcp": 70,
            "Avg": 122,
            "Gms": 3,
            "Pins": 366,
            "Hgs": 130,
            "HSS": 366
          }
        ]
      },
      {
        "name": "Skandia Warriors",
        "players": [
          {
            "name": "Michael Henderson",
            "Hcp": 20,
            "Avg": 177,
            "Gms": 3,
            "Pins": 536,
            "Hgs": 182,
            "HSS": 536
          },
          {
            "name": "Paul Gardner",
            "Hcp": 38,
            "Avg": 157,
            "Gms": 3,
            "Pins": 536,
            "Hgs": 182,
            "HSS": 536
          },
          {
            "name": "Barry Henderson",
            "Hcp": 89,
            "Avg": 101,
            "Gms": 3,
            "Pins": 311,
            "Hgs": 112,
            "HSS": 311
          },
          {
            "name": "Colin Argyle",
            "Hcp": 28,
            "Avg": 168,
            "Gms": 3,
            "Pins": 391,
            "Hgs": 170,
            "HSS": 391
          }
        ]
      }
    ]
  }
]
